odoo/addons/mass_mailing_contact_partner/README.rst
odoo/addons/mass_mailing_contact_partner/__init__.py
odoo/addons/mass_mailing_contact_partner/__manifest__.py
odoo/addons/mass_mailing_contact_partner/i18n/es.po
odoo/addons/mass_mailing_contact_partner/i18n/it.po
odoo/addons/mass_mailing_contact_partner/i18n/mass_mailing_contact_partner.pot
odoo/addons/mass_mailing_contact_partner/models/__init__.py
odoo/addons/mass_mailing_contact_partner/models/mailing_contact.py
odoo/addons/mass_mailing_contact_partner/models/res_partner.py
odoo/addons/mass_mailing_contact_partner/readme/CONTRIBUTORS.rst
odoo/addons/mass_mailing_contact_partner/readme/DESCRIPTION.rst
odoo/addons/mass_mailing_contact_partner/static/description/icon.png
odoo/addons/mass_mailing_contact_partner/static/description/index.html
odoo/addons/mass_mailing_contact_partner/tests/__init__.py
odoo/addons/mass_mailing_contact_partner/tests/test_mass_mailing_contact_partner.py
odoo/addons/mass_mailing_contact_partner/views/mailing_contact.xml
odoo14_addon_mass_mailing_contact_partner-14.0.1.0.1.dev14.dist-info/METADATA
odoo14_addon_mass_mailing_contact_partner-14.0.1.0.1.dev14.dist-info/WHEEL
odoo14_addon_mass_mailing_contact_partner-14.0.1.0.1.dev14.dist-info/top_level.txt
odoo14_addon_mass_mailing_contact_partner-14.0.1.0.1.dev14.dist-info/RECORD
